{"u11 garcons":[{"nom":"JARRY Nylann","club":"Perpignan"},{"nom":"LASSALLE Guerlain","club":"Perpignan"},{"nom":"LAURENT Benjamin","club":"Saint Cyprien"},{"nom":"NAMECH Raphael","club":"Saint Cyprien"},{"nom":"NICOLLET Soren","club":"GMBA"},{"nom":"RAULO Anton","club":"Limoges"},{"nom":"STUBER L\u00e9o","club":"Saint Cyprien"},{"nom":"VARESIS Filippos","club":"RMA"},{"nom":"CHEUTIN Hugo","club":"Le Barp"}],"u11 filles":[{"nom":"CARBONNEL Lise","club":"Saint Cyprien"},{"nom":"DAULY Alice","club":"CJF Saint-Malo"},{"nom":"DESAIZE Diane","club":"CJF Saint-Malo"},{"nom":"GAUCHER Julia","club":"Perpignan"},{"nom":"VARESIS Zakelina","club":"RMA"}],"u13 garcons":[{"nom":"ARTEAGA Joan","club":"Font-Romeu"},{"nom":"BANYULS Antoine","club":"Perpignan"},{"nom":"BEN HAMED Rayan","club":"VGA"},{"nom":"BOTREAU Raphael","club":"Antony"},{"nom":"COLAS Louis Victor","club":"RMA"},{"nom":"COURCELLES Rapha\u00ebl","club":"Perpignan"},{"nom":"DHIVERS Benoit Joseph","club":"Pamiers"},{"nom":"DUMAINE C\u00e9lyan","club":"Perpignan"},{"nom":"HAMON ROUSSEL Benjamin","club":"CJF Saint-Malo"},{"nom":"HERNANDEZ Hugo","club":"Perpignan"},{"nom":"JEROME Simon","club":"CJF Saint-Malo"},{"nom":"LEGRET Lucien","club":"CJF Saint-Malo"},{"nom":"NDZANG NYANGONE Nolan","club":"Perpignan"},{"nom":"NICOLLET Alec","club":"GMBA"},{"nom":"PARQUET Valentin","club":"VGA"},{"nom":"ROUSSEAU Lucas","club":"VGA"},{"nom":"LEMOINE Baptiste","club":"Antony"}],"u13 filles":[{"nom":"CHEUTIN Ana","club":"LBVE"},{"nom":"COX Elo\u00efse","club":"CJF Saint-Malo"},{"nom":"DEHIBA Ines","club":"VGA"},{"nom":"DESCHAMPS Emeline","club":"VGA"},{"nom":"DHEU Meline","club":"Meaux"},{"nom":"DUCASSY Violette","club":"Perpignan"},{"nom":"GARCIA Jeanne","club":"Perpignan"},{"nom":"GERARD CHEDMAIL Rose","club":"CJF Saint-Malo"},{"nom":"LAURET Anielle","club":"Perpignan"},{"nom":"MONNOT Juliette","club":"RMA"},{"nom":"PINSON Le\u00efa","club":"CJF Saint-Malo"},{"nom":"POUX CAPREDON Lucile","club":"Brie"},{"nom":"PRIEUR Valentine","club":"CJF Saint-Malo"},{"nom":"ROUZEIK Syrine","club":"RMA"},{"nom":"SOUCI RAYA Lilia","club":"Perpignan"},{"nom":"VILA L\u00e9onie","club":"Perpignan"},{"nom":"ZIMMERMANN Jeanne","club":"RMA"}],"u15 garcons":[{"nom":"BOUCHET Jules","club":"Salanque"},{"nom":"CREPIN BELLANGE Louis","club":"Antony"},{"nom":"DAULY Malo","club":"CJF Saint-Malo"},{"nom":"DELMAU Adrien","club":"Salanque"},{"nom":"DESCHAMPS Mathis","club":"VGA"},{"nom":"ERCILBENGOA Paul","club":"Antony"},{"nom":"ERCILBENGOA Arthur","club":"Antony"},{"nom":"GOUNELLE Antoine","club":"RMA"},{"nom":"HAUBERTIN Th\u00e9odore","club":"CJF Saint-Malo"},{"nom":"JARDRIX Guillem","club":"Perpignan"},{"nom":"JUFFIN Cl\u00e9ment","club":"Salanque"},{"nom":"LE GENDRE Elouan","club":"VGA"},{"nom":"LEJEUNE Tim\u00e9o","club":"Meaux"},{"nom":"MAUPEU Tom","club":"Pamiers"},{"nom":"MOYNE-HARSCOAT Josquin","club":"Salanque"},{"nom":"NOTTON Thimoth\u00e9e","club":"VGA"},{"nom":"PEYKOV Micha\u00ebl","club":"RMA"},{"nom":"SEVAT Antonin","club":"Meaux"},{"nom":"SINTES Joan","club":"Salanque"},{"nom":"VANDENBORRE Oscar","club":"Font-Romeu"}],"u15 filles":{"0":{"nom":"AMAR Ad\u00e8le","club":"Antony"},"1":{"nom":"BETTENS Jos\u00e9phine","club":"VGA"},"2":{"nom":"CARNEC Dina","club":"RMA"},"3":{"nom":"CERDA BERTRAN Martina","club":"Font-Romeu"},"4":{"nom":"DANIEL Laura","club":"CJF Saint-Malo"},"5":{"nom":"DOUCENDE Lilou","club":"Font-Romeu"},"6":{"nom":"DURET BUFFIER Ma\u00e9","club":"Perpignan"},"7":{"nom":"GAZAGNE Pom","club":"RMA"},"8":{"nom":"GEORGE Elli","club":"RMA"},"9":{"nom":"GIRARDIN Charlotte","club":"Perpignan"},"10":{"nom":"IKSIL Alexandra","club":"RMA"},"11":{"nom":"LABKER Aya","club":"Perpignan"},"12":{"nom":"LEJEUNE Lina","club":"Meaux"},"13":{"nom":"LOPEZ Alba","club":"Perpignan"},"14":{"nom":"MARATIER Chlo\u00e9","club":"Perpignan"},"15":{"nom":"MARATIER Lisa","club":"Perpignan"},"16":{"nom":"MAS Marion","club":"Perpignan"},"18":{"nom":"NYBELEN ALEXANDRE Lilou","club":"Salanque"},"19":{"nom":"RAULO Marion","club":"Limoges"},"20":{"nom":"ROUZEIK Lina","club":"Antony"},"22":{"nom":"VILA Valentine","club":"Perpignan"}},"u17 hommes":{"0":{"nom":"ARENS Jules","club":"VGA"},"1":{"nom":"BLANCHET Johan","club":"Antony"},"2":{"nom":"CANOT Alexis","club":"Mussidan P\u00e9rigord"},"3":{"nom":"CHEYMOL Baptiste","club":"RMA"},"4":{"nom":"DHEU Arthur","club":"Meaux"},"5":{"nom":"DHIVERS Nathanael","club":"Pamiers"},"6":{"nom":"DUMORTIER Mathieu","club":"VGA"},"7":{"nom":"FRANZETTI Lucas","club":"Saint Cyprien"},"8":{"nom":"GAZENGEL Erwan","club":"CJF Saint-Malo"},"9":{"nom":"GELLON Quentin","club":"VGA"},"10":{"nom":"GIRHARD Tilio","club":"Perpignan"},"11":{"nom":"LAZERAS Paul","club":"Salanque"},"12":{"nom":"LERIQUE Alessandro","club":"RMA"},"13":{"nom":"LOPEZ Pablo","club":"Perpignan"},"15":{"nom":"MARATIER Jules","club":"Perpignan"},"16":{"nom":"MAZEROLLES Martin","club":"CJF Saint-Malo"},"17":{"nom":"MERROUCHE BARD Constant","club":"Antony"},"18":{"nom":"NAMIECH Noam","club":"Saint Cyprien"},"19":{"nom":"NGUYEN Thibault","club":"Perpignan"},"20":{"nom":"PREVOSTO Mael","club":"Antony"},"21":{"nom":"REGEARD Noa","club":"CJF Saint-Malo"},"22":{"nom":"ROBESCU--MUNOZ Manael","club":"LRPMS"},"23":{"nom":"SAUVADET Vadim","club":"RMA"},"24":{"nom":"TAUREL Alexis","club":"VGA"},"25":{"nom":"TENEZE Lilian","club":"RMA"}},"u17 femmes":{"0":{"nom":"BAUDRELOT Jeanne","club":"Font-Romeu"},"1":{"nom":"BERNARD Lyse","club":"CJF Saint-Malo"},"2":{"nom":"BLIN Mathilda","club":"NPS"},"3":{"nom":"CARBONNEL Chlo\u00e9","club":"Saint Cyprien"},"4":{"nom":"CLEGUER Ana\u00eblle","club":"RMA"},"5":{"nom":"ESTEVIN Charlotte","club":"Salanque"},"6":{"nom":"FREDET GAU L\u00e9anne","club":"Saint Cyprien"},"7":{"nom":"GREMILLIER Romane","club":"Meaux"},"8":{"nom":"HANAIZI PATRICIO Alba","club":"RMA"},"9":{"nom":"LARGE Faustine","club":"Perpignan"},"10":{"nom":"L\u00c9ANDRA Thibot","club":"NPS"},"12":{"nom":"LE PORT Z\u00e9lie","club":"CJF Saint-Malo"},"13":{"nom":"PORLAN RAOUX Camille","club":"Saint Cyprien"},"14":{"nom":"SAULAIS Chlo\u00e9","club":"Perpignan"},"15":{"nom":"SEREZAT Zo\u00e9","club":"Salanque"}},"u19 hommes":[{"nom":"BLANCHET Dilan","club":"Antony"},{"nom":"GUILBAUD No\u00e9","club":"Perpignan"},{"nom":"LEJEUNE Mathis","club":"Meaux"},{"nom":"MAUPEU Loris","club":"Pamiers"},{"nom":"PENAS Jules","club":"Antony"},{"nom":"VAN LOOCKE Thomas","club":"Alpha Provence"}],"u19 femmes":[{"nom":"DAVID Alyson","club":"Pamiers"},{"nom":"DUMORTIER Camille","club":"VGA"},{"nom":"LABESSE Lou","club":"RMA"},{"nom":"MARCHAND Emma","club":"Perpignan"},{"nom":"PRATS ALAMI Alice","club":"Perpignan"}],"u22 hommes":[{"nom":"CAUDAN Mathieu","club":"CJF Saint-Malo"},{"nom":"DELBES Thomas","club":"RMA"},{"nom":"LOUIS Cyril","club":"Antony"}],"u22 femmes":[{"nom":"ANNEQUIN Suane","club":"Brie"},{"nom":"BOUSQUET Violette","club":"Pamiers"},{"nom":"BRISSARD Lucia","club":"Perpignan"},{"nom":"CHASTAGNER Agathe","club":"Antony"},{"nom":"FOSSEUX Charlotte","club":"RMA"},{"nom":"PLAS Ma\u00eblys","club":"NPS"},{"nom":"SINTES Liz\u00e9a","club":"Salanque"}],"senior hommes":[{"nom":"ATGER William","club":"Antony"},{"nom":"BRUYR Julien","club":"Saint Cyprien"},{"nom":"COULON Vincent","club":"Pentathlon B\u00e9arnais"},{"nom":"DELAMARRE Baptiste","club":"CJF Saint-Malo"},{"nom":"FERGE Malcom Alexis","club":"RMA"},{"nom":"GUILBAUD Thomas","club":"Perpignan"},{"nom":"LAMBOLEZ Audric","club":"GMBA"},{"nom":"LOUBET Brice","club":"GMBA"},{"nom":"MTIR Mohamed","club":"NPS"},{"nom":"PAILLER Antoine","club":"Brie"}],"senior femmes":{"0":{"nom":"CORMIER Agathe","club":"CJF Saint-Malo"},"1":{"nom":"DELAMARRE Alice","club":"CJF Saint-Malo"},"2":{"nom":"DELAMARRE Diane","club":"CJF Saint-Malo"},"4":{"nom":"DENOYES Louise","club":"RMA"},"5":{"nom":"DOUCHEZ Gaelle","club":"Brie"},"6":{"nom":"GENOLINI Camille","club":"Brie"},"7":{"nom":"MICHON Victoria","club":"CJF Saint-Malo"},"8":{"nom":"SOULAS Astrid","club":"RMA"}},"m40 hommes":[{"nom":"AMAR Gr\u00e9goire","club":"Antony"},{"nom":"BOTREAU Ronan","club":"Antony"},{"nom":"CONDOU-DARRACQ Fr\u00e9d\u00e9ric","club":"Pentathlon B\u00e9arnais"},{"nom":"DAULY Arnaud","club":"CJF Saint-Malo"},{"nom":"DOMENGE Nicolas","club":"Meaux"},{"nom":"ESTEVIN Pierrick","club":"Salanque"},{"nom":"FENRICH Florent","club":"Meaux"},{"nom":"FOVEAUX Arnaud","club":"Pamiers"},{"nom":"LEJEUNE Frank","club":"Meaux"},{"nom":"MARATIER Julien","club":"Perpignan"},{"nom":"MICHELOSI Johan","club":"Alpha Provence"},{"nom":"POUX Jerome","club":"Brie"},{"nom":"ROBESCU Viorel-Cristian","club":"LRPMS"},{"nom":"SEGRET Guillaume","club":"Brie"},{"nom":"SINTES Jean-Luc","club":"Salanque"},{"nom":"VINCENS Benoit","club":"Pentathlon Pennois"}],"m40 femmes":[{"nom":"BARBIER Aur\u00e9lie","club":"GMBA"},{"nom":"BONNEAUD Marine","club":"Saint Cyprien"},{"nom":"CAPREDON Laurence","club":"Brie"},{"nom":"DANIEL M\u00e9lanie","club":"CJF Saint-Malo"},{"nom":"FENRICH LEJEUNE Aurelie","club":"Meaux"},{"nom":"MARATIER Julie","club":"Perpignan"}],"m50 hommes":{"0":{"nom":"ALAMI Adil","club":"Perpignan"},"1":{"nom":"ANNEQUIN Franck","club":"Brie"},"3":{"nom":"DAVID Dorian","club":"Pamiers"},"4":{"nom":"DJEMILI Fay\u00e7al","club":"NPS"},"5":{"nom":"DUMORTIER St\u00e9phane","club":"VGA"},"6":{"nom":"GUTIERREZ MOUGIN Arnaud","club":"CJF Saint-Malo"},"8":{"nom":"JUFFIN Gilles","club":"St\u00e9phanois"},"9":{"nom":"LAFARGUE Patrice","club":"Antony"},"10":{"nom":"LOUIS Sylvain","club":"Antony"},"11":{"nom":"MAUPEU Christophe","club":"Pamiers"},"12":{"nom":"NAMIECH Gr\u00e9gory","club":"Saint Cyprien"},"13":{"nom":"NICOLLET Boris","club":"GMBA"},"14":{"nom":"RAKATONDRAVAO Olivier","club":"RMA"},"15":{"nom":"THIBOT S\u00e9bastien","club":"NPS"},"16":{"nom":"TOUREL Jean Sebastien","club":"Perpignan"},"17":{"nom":"TRAN Michel","club":"Pentathlon B\u00e9arnais"}},"m50 femmes":[{"nom":"BLANCARD Sylvaine","club":"CJF Saint-Malo"},{"nom":"DENOYES Nathalie","club":"RMA"},{"nom":"FASSI FEHRI Corinne","club":"Perpignan"},{"nom":"GENEVET Christine","club":"Meaux"},{"nom":"LEVY Milfried","club":"RMA"},{"nom":"LOISEL Val\u00e9rie","club":"RMA"},{"nom":"ORLIANGES Caroline","club":"US M\u00e9tro"},{"nom":"SAUVADET TOLOCHKO Natalia","club":"RMA"},{"nom":"TRAN Pascale","club":"Pentathlon B\u00e9arnais"}],"m60 hommes":{"0":{"nom":"BOUSQUET Pierre","club":"Pamiers"},"1":{"nom":"CANOT Jean-Michel","club":"Mussidan P\u00e9rigord"},"2":{"nom":"DELAMARRE Philippe","club":"CJF Saint-Malo"},"3":{"nom":"DUBUCQ Dominique","club":"Pentathlon B\u00e9arnais"},"4":{"nom":"GARDIN Thierry","club":"CJF Saint-Malo"},"6":{"nom":"LAVAUD Fr\u00e9d\u00e9ric","club":"US M\u00e9tro"},"7":{"nom":"LOCARINI Fabrice","club":"Meaux"},"8":{"nom":"MAGHIN Thierry","club":"Brie"},"9":{"nom":"MONDOT Dominique","club":"CEPMG"},"10":{"nom":"TRINCAL Alain","club":"RMA"}},"m60 femmes":[{"nom":"DUFEYTE Marie-Pierre","club":"Pentathlon B\u00e9arnais"},{"nom":"THOREUX DUMAS Patricia","club":"RMA"}],"m70 hommes":[{"nom":"JOSEPH Christian","club":"Perpignan"}],"m70 femmes":[{"nom":"JOLIVET Nad\u00e8ge","club":"RMA"}],"para hommes":[{"nom":"BOUYOUCEF Omar","club":"CEPMG"}],"para femmes":[{"nom":"REGNAULD Olivia","club":"Perpignan"}]}